ultrasatutils/__init__.py
ultrasatutils/data/ultrasat_bandpass_center.csv
ultrasatutils/data/ultrasat_snr_G_5deg.csv
ultrasatutils/utils.py
ultrasatutils-0.1.0.dist-info/LICENSE
ultrasatutils-0.1.0.dist-info/METADATA
ultrasatutils-0.1.0.dist-info/WHEEL
ultrasatutils-0.1.0.dist-info/RECORD
