Metadata-Version: 2.1
Name: ultrasatutils
Version: 0.1.0
Summary: 
Author: Tom Barclay
Author-email: barclay.astro@gmail.com
Requires-Python: >=3.8,<4.0
Classifier: Programming Language :: Python :: 3
Classifier: Programming Language :: Python :: 3.8
Classifier: Programming Language :: Python :: 3.9
Classifier: Programming Language :: Python :: 3.10
Classifier: Programming Language :: Python :: 3.11
Classifier: Programming Language :: Python :: 3.12
Requires-Dist: MeanStars (>=3.0.0,<4.0.0)
Requires-Dist: astropy (>=5.0.4,<6.0.0)
Requires-Dist: numpy (>=1.22.3,<2.0.0)
Requires-Dist: pandas (>=2.0.0,<3.0.0)
Requires-Dist: pysynphot (>=2.0.0)
